[
  {
    "name": "Telefono",
    "aliases": [
      "Telefonino",
      "Cellulare",
      "Phone"
    ],
    "description": "Il tuo cellulare, pronto per essere usato.",
    "isPickable": true
  },
  {
    "name": "Fiammiferi",
    "aliases": [
      "Fiammifero",
      "ScatolaFiammiferi",
      "Accendino"
    ],
    "description": "Una scatola di fiammiferi secchi.",
    "isPickable": true
  },
  {
    "name": "Tavolo",
    "aliases": [
      "Tavolino",
      "Banco",
      "Tavolino",
      "Scrivania"
    ],
    "description": "Un tavolino su cui giacciono una candela e un foglio piegato.",
    "isPickable": false
  },
  {
    "name": "Candela",
    "aliases": [
      "Lume",
      "Luce",
      "Fiamma"
    ],
    "description": "Una candela spenta, consumata dal tempo.",
    "isPickable": true
  },
  {
    "name": "Foglio",
    "aliases": [
      "Foglietto",
      "Indizio",
      "Carta",
      "Pagina"
    ],
    "description": "Un foglio con un indizio: \u0027Verso nord, la luce trova ciò che l\u0027\u0027ombra nasconde.\u0027",
    "isPickable": true
  },
  {
    "name": "Camino",
    "aliases": [
      "Caminetto",
      "Fuoco",
      "Focolare"
    ],
    "description": "Un grande camino annerito. Sopra c\u0027è una vecchia chiave.",
    "isPickable": false
  },
  {
    "name": "Tappeto",
    "aliases": [
      "Tappetino",
      "Stuoia"
    ],
    "description": "Un vecchio tappeto logoro. Uno scrigno giace su di esso.",
    "isPickable": false
  },
  {
    "name": "Chiave",
    "aliases": [
      "Chiavetta",
      "ChiaveFerro"
    ],
    "description": "Una vecchia chiave di ferro.",
    "isPickable": true
  },
  {
    "list": [
      {
        "name": "Amuleto",
        "aliases": [
          "Ciondolo",
          "Pendente",
          "Collana",
          "Protezione"
        ],
        "description": "Un amuleto d\u0027argento a forma di goccia.",
        "isPickable": true
      }
    ],
    "name": "Scrigno",
    "aliases": [
      "Cassetta",
      "Cofanetto",
      "Baule",
      "Cassa"
    ],
    "description": "Uno scrigno antico con serratura arrugginita.",
    "isPickable": false
  },
  {
    "name": "Scaffale",
    "aliases": [
      "Ripiano",
      "Mensola",
      "Palchetto"
    ],
    "description": "Uno scaffale con libri bruciati. Un diario sembra intatto.",
    "isPickable": false
  },
  {
    "name": "Diario",
    "aliases": [
      "Libro",
      "Quaderno",
      "Manoscritto",
      "Memoria"
    ],
    "description": "Un diario con simboli e istruzioni per un rituale.",
    "isPickable": true
  },
  {
    "name": "Altare",
    "aliases": [
      "Tavolo",
      "Piattaforma"
    ],
    "description": "Un altare di pietra con un\u0027iscrizione.",
    "isPickable": false
  }
]